matrix/__init__.py
matrix/_version.py
matrix/approximate.py
matrix/calculate.py
matrix/constants.py
matrix/decompositions.py
matrix/errors.py
matrix/nearest.py
matrix/permute.py
matrix/util.py
matrix/_util/__init__.py
matrix/_util/roots.py
matrix/approximation/__init__.py
matrix/approximation/positive_semidefinite/GMW_SE.py
matrix/approximation/positive_semidefinite/Reimer.py
matrix/approximation/positive_semidefinite/__init__.py
matrix/dense/__init__.py
matrix/dense/calculate.py
matrix/dense/constants.py
matrix/dense/permute.py
matrix/dense/util.py
matrix/sparse/__init__.py
matrix/sparse/calculate.py
matrix/sparse/constants.py
matrix/sparse/permute.py
matrix/sparse/util.py
matrix/tests/__init__.py
matrix/tests/random.py
matrix/tests/test_append_block_decomposition.py
matrix/tests/test_approximate.py
matrix/tests/test_convert.py
matrix/tests/test_decompose.py
matrix/tests/test_equal.py
matrix/tests/test_io.py
matrix/tests/test_is_finite.py
matrix/tests/test_is_invertable.py
matrix/tests/test_is_positive_definite.py
matrix/tests/test_multiply.py
matrix/tests/test_permute.py
matrix/tests/test_solve.py
matrix/tests/test_solver_depressed_cubic.py
matrix_decomposition-1.2.dist-info/LICENSE.txt
matrix_decomposition-1.2.dist-info/METADATA
matrix_decomposition-1.2.dist-info/WHEEL
matrix_decomposition-1.2.dist-info/top_level.txt
matrix_decomposition-1.2.dist-info/RECORD
