Metadata-Version: 2.1
Name: matrix-decomposition
Version: 1.2
Summary: This library allows to approximate Hermitian (dense and sparse) matrices by positive definite matrices. Furthermore it allows to decompose (factorize) positive definite matrices and solve associated systems of linear equations.
Home-page: https://github.com/jor-/matrix_decomposition
Author: Joscha Reimer
Author-email: jor@informatik.uni-kiel.de
License: AGPL
Keywords: approximation Hermitian dense sparse matrix matrices positive definite decompose factorize decomposition factorization linear equation equations Cholesky
Platform: UNKNOWN
Classifier: Development Status :: 5 - Production/Stable
Classifier: Intended Audience :: Science/Research
Classifier: Topic :: Scientific/Engineering :: Mathematics
Classifier: Topic :: Software Development :: Libraries :: Python Modules
Classifier: Topic :: Utilities
Classifier: License :: OSI Approved :: GNU Affero General Public License v3 or later (AGPLv3+)
Classifier: Programming Language :: Python
Requires-Python: >=3.7
Requires-Dist: numpy (>=1.15)
Requires-Dist: scipy (>=0.19)
Provides-Extra: decompose_sparse
Requires-Dist: scikit-sparse (>=0.4.2) ; extra == 'decompose_sparse'
